Metadata-Version: 1.1
Name: testit-allure-adaptor
Version: 0.1.9
Summary: Allure report adaptor for Test IT
Home-page: https://pypi.org/project/testit-allure-adaptor/
Author: Pavel Butuzov
Author-email: pavel.butuzov@testit.software
License: Apache-2.0
Platform: UNKNOWN
Classifier: Programming Language :: Python :: 3
Classifier: Programming Language :: Python :: 3.6
Classifier: Programming Language :: Python :: 3.7
Classifier: Programming Language :: Python :: 3.8
Classifier: Programming Language :: Python :: 3.9
